{
    "$schema": "https://schemastore.azurewebsites.net/schemas/json/sarif-2.1.0-rtm.5.json",
    "version": "2.1.0",
    "runs": [
        {
            "tool": {
                "driver": {
                    "name": "Thang's Agent Analyzer",
                    "rules": [
                        {
                            "id": "BENIGN-001",
                            "name": "VerifiedBenignBehavior",
                            "shortDescription": {
                                "text": "Identifies behaviors confirmed to be legitimate and non-malicious."
                            },
                            "fullDescription": {
                                "text": "This rule flags behaviors that, after thorough analysis and reconciliation with external threat intelligence, are confirmed to be part of legitimate software functionality and pose no security threat. This includes common system operations, file access within expected boundaries, and use of standard utilities for their intended purposes."
                            },
                            "helpUri": "https://example.com/benign-001-help"
                        }
                    ]
                }
            },
            "results": [
                {
                    "ruleId": "BENIGN-001",
                    "level": "note",
                    "message": {
                        "text": "The 'screenshot' skill has been verified as legitimate and non-malicious. External threat intelligence strongly refutes any suspicion of malicious intent and confirms that the observed behaviors (accessing filesystem, executing shell commands like 'fd', 'Get-ChildItem', 'find' for image files in user directories) are consistent with a benign screenshot viewing utility. No specific suspicious lines were identified in the initial analysis. The skill's intent is to locate and display recent screenshots, which is a legitimate function."
                    },
                    "locations": [
                        {
                            "artifactLocation": {
                                "uri": "skill.py"
                            }
                        }
                    ],
                    "properties": {
                        "threat_score": 0,
                        "confidence": 100,
                        "evidence_strength": "strong",
                        "verification_result": "confirmed",
                        "threat_category": "None",
                        "skill_url": "N/A"
                    }
                }
            ]
        }
    ]
}